Metadata-Version: 2.1
Name: Engezny
Version: 1.2
Summary: Quick generation for charts from DataFrame
Home-page: https://github.com/MDSH14
Author: Mohammed Saleh
Author-email: MohammedSaleh@ieee.org
License: MIT
Download-URL: https://github.com/MDSH14/Engezny/archive/refs/tags/1.2.tar.gz
Keywords: Analysis,Data,Charts
Platform: UNKNOWN
Classifier: Development Status :: 4 - Beta
Classifier: Intended Audience :: Developers
Classifier: Topic :: Software Development :: Build Tools
Classifier: License :: OSI Approved :: MIT License
Classifier: Programming Language :: Python :: 3
Classifier: Programming Language :: Python :: 3.4
Classifier: Programming Language :: Python :: 3.5
Classifier: Programming Language :: Python :: 3.6
